pysparkgui/__init__.py
pysparkgui/__main__.py
pysparkgui/_authorization.py
pysparkgui/_environment.py
pysparkgui/_path.py
pysparkgui/_server_api.py
pysparkgui/_types.py
pysparkgui/config.py
pysparkgui/df_manager.py
pysparkgui/grid.py
pysparkgui/spark_df_manager.py
pysparkgui/spark_wrangler.py
pysparkgui/version.py
pysparkgui/wrangler.py
pysparkgui/assets/img/long_to_wide.png
pysparkgui/assets/img/viz_and_profile_tabs_in_databricks_display.png
pysparkgui/assets/img/wide_to_long.png
pysparkgui/datasets/.DS_Store
pysparkgui/datasets/__init__.py
pysparkgui/datasets/get_datasets.py
pysparkgui/datasets/sales.csv
pysparkgui/datasets/titanic.csv
pysparkgui/datasets/__pycache__/__init__.cpython-37.pyc
pysparkgui/datasets/__pycache__/__init__.cpython-38.pyc
pysparkgui/datasets/__pycache__/__init__.cpython-39.pyc
pysparkgui/datasets/__pycache__/get_datasets.cpython-37.pyc
pysparkgui/datasets/__pycache__/get_datasets.cpython-38.pyc
pysparkgui/datasets/__pycache__/get_datasets.cpython-39.pyc
pysparkgui/edaviz/__init__.py
pysparkgui/edaviz/__modules__.py
pysparkgui/edaviz/base.py
pysparkgui/edaviz/constants.py
pysparkgui/edaviz/data_types.py
pysparkgui/edaviz/interactive_histogram.py
pysparkgui/edaviz/plots.py
pysparkgui/edaviz/timeseries_plot.py
pysparkgui/edaviz/utils.py
pysparkgui/edaviz/z_legacy.py
pysparkgui/helper/__init__.py
pysparkgui/helper/error.py
pysparkgui/helper/gui_outlets.py
pysparkgui/helper/gui_viewables.py
pysparkgui/helper/utils.py
pysparkgui/loaders/__init__.py
pysparkgui/loaders/databricks_database_table_loader.py
pysparkgui/loaders/dummy_data.py
pysparkgui/loaders/spark_table_loader.py
pysparkgui/plugins/__init__.py
pysparkgui/plugins/_adapters.py
pysparkgui/plugins/_base_classes.py
pysparkgui/plugins/_registry.py
pysparkgui/plugins/_utils.py
pysparkgui/setup/__init__.py
pysparkgui/setup/_extensions.py
pysparkgui/setup/file_logger.py
pysparkgui/setup/import_.py
pysparkgui/setup/ipython_display.py
pysparkgui/setup/module_view.py
pysparkgui-0.5.2.dist-info/LICENSE
pysparkgui-0.5.2.dist-info/METADATA
pysparkgui-0.5.2.dist-info/WHEEL
pysparkgui-0.5.2.dist-info/top_level.txt
pysparkgui-0.5.2.dist-info/RECORD
