Metadata-Version: 2.1
Name: pysparkgui
Version: 0.5.2
Summary: pysparkgui - a GUI for pandas
Home-page: https://pysparkgui.8080labs.com
Author: Databricks
Author-email: pysparkgui-feedback@databricks.com
License: Databricks Proprietary License
Keywords: pandas,gui,jupyter,widgets,ipython
Classifier: Programming Language :: Python :: 3.6
Classifier: Programming Language :: Python :: 3.7
Classifier: Programming Language :: Python :: 3.8
Classifier: Programming Language :: Python :: 3.9
Classifier: Programming Language :: Python :: 3.10
Requires-Python: >=3.6
License-File: LICENSE
Requires-Dist: attrs (>=20.3.0)
Requires-Dist: cryptography (>=2.6.1)
Requires-Dist: ipywidgets (<8.0.0,>=7.6.0)
Requires-Dist: jedi (<1.0.0)
Requires-Dist: pandas (<2.0.0,>=1.1.0)
Requires-Dist: packaging (>=19.2)
Requires-Dist: plotly (<6.0.0,>=4.9.0)
Requires-Dist: ppscore (<2.0.0,>=1.2.0)
Requires-Dist: psutil (<6,>=5.4.2)
Requires-Dist: pygments
Requires-Dist: ipyslickgrid (==0.0.3)
Requires-Dist: scikit-learn (<2.0.0,>=0.20.2)
Requires-Dist: statsmodels (<1.0.0)
Requires-Dist: toml (>=0.10.0)
Requires-Dist: xlrd (>=1.0.0)
